jyutping2characters/__init__.py
jyutping2characters/cli.py
jyutping2characters/data_builder.py
jyutping2characters/transcriber.py
jyutping2characters-0.1.0.dist-info/licenses/LICENSE
jyutping2characters-0.1.0.dist-info/METADATA
jyutping2characters-0.1.0.dist-info/WHEEL
jyutping2characters-0.1.0.dist-info/entry_points.txt
jyutping2characters-0.1.0.dist-info/top_level.txt
jyutping2characters-0.1.0.dist-info/RECORD
