Metadata-Version: 2.4
Name: jyutping2characters
Version: 0.1.0
Summary: Convert Jyutping romanization to Traditional Chinese characters
Author-email: James Zheng <endernoke@gmail.com>
License-Expression: MIT
Project-URL: Homepage, https://github.com/endernoke/jyutping2characters
Project-URL: Issues, https://github.com/endernoke/jyutping2characters/issues
Project-URL: Repository, https://github.com/endernoke/jyutping2characters.git
Keywords: jyutping,cantonese,chinese,transcription,translation,backtranslation,romanization,nlp,linguistics
Classifier: Development Status :: 4 - Beta
Classifier: Intended Audience :: Developers
Classifier: Operating System :: OS Independent
Classifier: Programming Language :: Python :: 3
Classifier: Programming Language :: Python :: 3.8
Classifier: Programming Language :: Python :: 3.9
Classifier: Programming Language :: Python :: 3.10
Classifier: Programming Language :: Python :: 3.11
Classifier: Programming Language :: Python :: 3.12
Classifier: Programming Language :: Python :: 3.13
Classifier: Topic :: Text Processing :: Linguistic
Classifier: Topic :: Software Development :: Libraries :: Python Modules
Classifier: Natural Language :: Chinese (Traditional)
Classifier: Topic :: Utilities
Requires-Python: >=3.8
License-File: LICENSE
Requires-Dist: appdirs>=1.4.0
Provides-Extra: dev
Requires-Dist: pytest>=7.0; extra == "dev"
Dynamic: license-file
